finsec/__init__.py
finsec/__meta__.py
finsec/base.py
finsec/config.py
finsec/constructors.py
finsec/enums.py
finsec/exceptions.py
finsec/exchanges.py
finsec/futures.py
finsec/misc.py
finsec/occ_symbology.py
finsec/options.py
finsec/quote_grid.py
finsec/quotes.py
finsec/serializer.py
finsec/utils.py
financial_security_classes-0.4.0.dist-info/LICENSE
financial_security_classes-0.4.0.dist-info/METADATA
financial_security_classes-0.4.0.dist-info/WHEEL
financial_security_classes-0.4.0.dist-info/top_level.txt
financial_security_classes-0.4.0.dist-info/RECORD
