Metadata-Version: 2.1
Name: financial-security-classes
Version: 0.4.0
Summary: Pure python financial securities dataclasses
Home-page: https://github.com/alienbrett/financial-security-classes
Author: Brett Graves
Author-email: alienbrett648@gmail.com
License: apache
Classifier: Natural Language :: English
Classifier: Programming Language :: Python
Classifier: Programming Language :: Python :: 3
Classifier: Programming Language :: Python :: 3.6
Classifier: Programming Language :: Python :: 3.7
Classifier: Programming Language :: Python :: 3.8
Classifier: Programming Language :: Python :: 3.9
Classifier: Programming Language :: Python :: 3.10
Classifier: Programming Language :: Python :: 3.11
Requires-Python: >=3.5
License-File: LICENSE
Requires-Dist: pandas
Requires-Dist: pydantic
Requires-Dist: tzdata
Requires-Dist: pytz ; python_version < "3.9"
Provides-Extra: all
Requires-Dist: black (==22.10.0) ; extra == 'all'
Requires-Dist: docutils (>=0.18.1) ; extra == 'all'
Requires-Dist: identify (>=1.4.20) ; extra == 'all'
Requires-Dist: myst-parser ; extra == 'all'
Requires-Dist: piccolo-theme ; extra == 'all'
Requires-Dist: pre-commit ; extra == 'all'
Requires-Dist: pypandoc (>=1.6.3) ; extra == 'all'
Requires-Dist: pytest ; extra == 'all'
Requires-Dist: pytest-cov ; extra == 'all'
Requires-Dist: pytest-flake8 ; extra == 'all'
Requires-Dist: setuptools ; extra == 'all'
Requires-Dist: sphinx-autobuild ; extra == 'all'
Requires-Dist: sphinx (>=3) ; extra == 'all'
Requires-Dist: sphinx-book-theme ; extra == 'all'
Requires-Dist: twine ; extra == 'all'
Requires-Dist: wheel ; extra == 'all'
Requires-Dist: watchdog (<1.0.0) ; (python_version < "3.6") and extra == 'all'
Requires-Dist: readthedocs-sphinx-search ; (python_version >= "3.6") and extra == 'all'
Provides-Extra: dev
Requires-Dist: black (==22.10.0) ; extra == 'dev'
Requires-Dist: identify (>=1.4.20) ; extra == 'dev'
Requires-Dist: pre-commit ; extra == 'dev'
Requires-Dist: setuptools ; extra == 'dev'
Requires-Dist: twine ; extra == 'dev'
Requires-Dist: wheel ; extra == 'dev'
Provides-Extra: docs
Requires-Dist: docutils (>=0.18.1) ; extra == 'docs'
Requires-Dist: myst-parser ; extra == 'docs'
Requires-Dist: piccolo-theme ; extra == 'docs'
Requires-Dist: pypandoc (>=1.6.3) ; extra == 'docs'
Requires-Dist: sphinx (>=3) ; extra == 'docs'
Requires-Dist: sphinx-autobuild ; extra == 'docs'
Requires-Dist: sphinx-book-theme ; extra == 'docs'
Requires-Dist: watchdog (<1.0.0) ; (python_version < "3.6") and extra == 'docs'
Requires-Dist: readthedocs-sphinx-search ; (python_version >= "3.6") and extra == 'docs'
Provides-Extra: test
Requires-Dist: pytest ; extra == 'test'
Requires-Dist: pytest-cov ; extra == 'test'
Requires-Dist: pytest-flake8 ; extra == 'test'
